crdb_mcpctl/__init__.py
crdb_mcpctl/cli.py
crdb_mcpctl/config.py
crdb_mcpctl/logging_config.py
crdb_mcpctl/utils.py
crdb_mcpctl-0.1.0.dist-info/licenses/LICENSE
crdb_mcpctl-0.1.0.dist-info/METADATA
crdb_mcpctl-0.1.0.dist-info/WHEEL
crdb_mcpctl-0.1.0.dist-info/entry_points.txt
crdb_mcpctl-0.1.0.dist-info/top_level.txt
crdb_mcpctl-0.1.0.dist-info/RECORD
