Metadata-Version: 2.4
Name: crdb-mcpctl
Version: 0.1.0
Summary: CLI for interacting with a CRDB-backed Model Context Protocol server
Author-email: Virag Tripathi <virag.tripathi@gmail.com>
License-Expression: MIT
Classifier: Development Status :: 4 - Beta
Classifier: Intended Audience :: Developers
Classifier: Topic :: Software Development :: Quality Assurance
Classifier: Programming Language :: Python :: 3
Classifier: Programming Language :: Python :: 3.7
Classifier: Programming Language :: Python :: 3.8
Classifier: Programming Language :: Python :: 3.9
Classifier: Programming Language :: Python :: 3.10
Classifier: Operating System :: OS Independent
Requires-Python: >=3.9
License-File: LICENSE
Requires-Dist: typer[all]>=0.12.3
Requires-Dist: requests>=2.31.0
Requires-Dist: pydantic>=2.6.4
Requires-Dist: PyYAML>=6.0.1
Requires-Dist: openai>=1.14.2
Requires-Dist: anthropic>=0.25.4
Requires-Dist: tenacity
Provides-Extra: dev
Requires-Dist: black; extra == "dev"
Requires-Dist: ruff; extra == "dev"
Requires-Dist: pytest; extra == "dev"
Requires-Dist: pytest-mock; extra == "dev"
Dynamic: license-file
